odoo/addons/l10n_br_sped_base/README.rst
odoo/addons/l10n_br_sped_base/__init__.py
odoo/addons/l10n_br_sped_base/__manifest__.py
odoo/addons/l10n_br_sped_base/i18n/l10n_br_sped_base.pot
odoo/addons/l10n_br_sped_base/models/__init__.py
odoo/addons/l10n_br_sped_base/models/res_partner.py
odoo/addons/l10n_br_sped_base/models/sped_declaration.py
odoo/addons/l10n_br_sped_base/models/sped_mixin.py
odoo/addons/l10n_br_sped_base/readme/CONTRIBUTORS.md
odoo/addons/l10n_br_sped_base/readme/DESCRIPTION.md
odoo/addons/l10n_br_sped_base/static/description/icon.png
odoo/addons/l10n_br_sped_base/static/description/index.html
odoo/addons/l10n_br_sped_base/tests/__init__.py
odoo/addons/l10n_br_sped_base/tests/demo_fake.txt
odoo/addons/l10n_br_sped_base/tests/sped_fake.py
odoo/addons/l10n_br_sped_base/tests/sped_fake_spec_9.py
odoo/addons/l10n_br_sped_base/tests/sped_mixin_fake.py
odoo/addons/l10n_br_sped_base/tests/test_sped_base.py
odoo/addons/l10n_br_sped_base/views/res_partner_view.xml
odoo/addons/l10n_br_sped_base/views/sped_base.xml
odoo_addon_l10n_br_sped_base-16.0.3.2.0.dist-info/METADATA
odoo_addon_l10n_br_sped_base-16.0.3.2.0.dist-info/WHEEL
odoo_addon_l10n_br_sped_base-16.0.3.2.0.dist-info/top_level.txt
odoo_addon_l10n_br_sped_base-16.0.3.2.0.dist-info/RECORD
